<?xml version="1.0" encoding="UTF-8" ?>
<odoo>
    <record id="view_invoice_line_tree" model="ir.ui.view">
        <field name="model">account.invoice.line</field>
        <field name="name">account.invoice.line.tree</field>
        <field name="priority" eval="999"/>
        <field name="arch" type="xml">
            <tree string="Invoice Line">
                <field name="name"/>
                <field name="account_id" groups="account.group_account_user"/>
                <field name="quantity"/>
                <field name="uom_id" groups="uom.group_uom"/>
                <field name="price_unit"/>
                <field name="discount" groups="base.group_no_one"/>
                <field name="price_subtotal" groups="account.group_show_line_subtotals_tax_excluded" sum="Total"/>
                <field name="price_total" groups="account.group_show_line_subtotals_tax_included" sum="Total"/>
                <field name="product_standard_price" invisible="1"/>
                <field name="move_price_unit" invisible="1"/>
                <field name="move_price_total" sum="Total Cost"/>
                <field name="currency_id" invisible="1"/>
            </tree>
        </field>
    </record>
    <record id="view_account_analytic_line_tree" model="ir.ui.view">
        <field name="model">account.analytic.line</field>
        <field name="name">account.analytic.line.tree</field>
        <field name="priority" eval="999"/>
        <field name="arch" type="xml">
            <tree string="Analytic Entries">
                <field name="date"/>
                <field name="name"/>
                <field name="account_id"/>
                <field name="general_account_id" groups="account.group_account_user"/>
                <field name="currency_id" invisible="1"/>
                <field name="company_id" groups="base.group_multi_company"/>
                <field name="unit_amount" sum="Quantity"/>
                <field name="amount" sum="Total"/>
            </tree>
        </field>
    </record>
</odoo>
